[{"1":0,"20":1,"21":1,"25":2,"26":3,"27":3,"29":4,"32":5,"35":6,"36":7,"39":8,"41":9,"42":10,"44":11,"45":12,"46":13,"49":14,"51":15,"53":16,"54":17,"55":18,"56":19,"57":20,"58":21,"60":22,"61":22,"62":22,"67":23,"70":24,"71":25,"73":26,"74":27,"75":28,"76":29,"77":30,"80":31,"81":32,"82":33,"83":34},["Evergreen","Andalusia","Beatrice","Brewton","Brooklyn","Castleberry","Coy","Dickinson","Excel","Flomaton","Florala","Franklin","Frisco City","Fulton","Goodway","Grove Hill","Kinston","Lenox","Lockhart","Mc Kenzie","Megargel","Mexia","Monroeville","Opp","Perdue Hill","Peterman","Range","Red Level","Repton","River Falls","Samson","Uriah","Vredenburgh","Whatley","Wing"],["AL|Alabama"]]